MANIFEST.in
README.txt
setup.py
sightcall_auth/__init__.py
sightcall_auth/config.py
sightcall_auth/extract.py
sightcall_auth/parse_p12.py
sightcall_auth/request.py
sightcall_auth.egg-info/PKG-INFO
sightcall_auth.egg-info/SOURCES.txt
sightcall_auth.egg-info/dependency_links.txt
sightcall_auth.egg-info/entry_points.txt
sightcall_auth.egg-info/requires.txt
sightcall_auth.egg-info/top_level.txt
tests/__init__.py
tests/test.py