Metadata-Version: 1.1
Name: sightcall-auth
Version: 0.1.1
Summary: Authenticate to the SightCall cloud
Home-page: #TODO
Author: Raphaël Boucher
Author-email: raphael.boucher@sightcall.com
License: GPL
Platform: UNKNOWN
Classifier: Programming Language :: Python
Classifier: Development Status :: 1 - Planning
Classifier: License :: OSI Approved
Classifier: Natural Language :: English
Classifier: Operating System :: OS Independent
Classifier: Programming Language :: Python :: 3.4
Classifier: Topic :: Communications
